README.txt
setup.py
docs/INSTALL.txt
docs/LICENSE.GPL
docs/LICENSE.txt
plonehrm/__init__.py
plonehrm.dutch.egg-info/PKG-INFO
plonehrm.dutch.egg-info/SOURCES.txt
plonehrm.dutch.egg-info/dependency_links.txt
plonehrm.dutch.egg-info/entry_points.txt
plonehrm.dutch.egg-info/namespace_packages.txt
plonehrm.dutch.egg-info/not-zip-safe
plonehrm.dutch.egg-info/paster_plugins.txt
plonehrm.dutch.egg-info/requires.txt
plonehrm.dutch.egg-info/top_level.txt
plonehrm/dutch/HISTORY.txt
plonehrm/dutch/__init__.py
plonehrm/dutch/browser.py
plonehrm/dutch/overrides.zcml