Metadata-Version: 1.0
Name: plonehrm.dutch
Version: 1.3.1
Summary: Dutch specific Plone HRM parts
Home-page: http://plone.org/products/plonehrm
Author: Zest Software
Author-email: info@zestsoftware.nl
License: GPL
Platform: UNKNOWN
Classifier: Framework :: Plone
Classifier: Programming Language :: Python
Classifier: Topic :: Software Development :: Libraries :: Python Modules
